sperryLabelImg/__init__.py
sperryLabelImg/app.py
sperrylabelimg-3.1.2.dist-info/METADATA
sperrylabelimg-3.1.2.dist-info/WHEEL
sperrylabelimg-3.1.2.dist-info/entry_points.txt
sperrylabelimg-3.1.2.dist-info/top_level.txt
sperrylabelimg-3.1.2.dist-info/RECORD
