Metadata-Version: 2.4
Name: sperrylabelimg
Version: 3.1.2
Summary: A GUI for labelling images customized for usage at Sperry Rail
Author-email: Sperry Rail Innovation <brooklyn.germa@sperryrail.com>
License: MIT
Project-URL: Homepage, https://gitlab.com/bGerma/customlabelimg
Project-URL: Repository, https://gitlab.com/bGerma/customlabelimg.git
Classifier: Development Status :: 3 - Alpha
Classifier: Intended Audience :: Developers
Classifier: License :: OSI Approved :: MIT License
Classifier: Programming Language :: Python :: 3
Classifier: Programming Language :: Python :: 3.7
Requires-Python: >=3.7
Requires-Dist: labelimg==1.8.6
Provides-Extra: dev
